openperf/__init__.py
openperf/main.py
openperf/benchmarks/__init__.py
openperf/benchmarks/data_science/__init__.py
openperf/benchmarks/data_science/bot_detection/BoDeGHa_bench.py
openperf/benchmarks/data_science/bot_detection/__init__.py
openperf/benchmarks/data_science/bot_detection/base_model_benmark.py
openperf/benchmarks/data_science/bot_detection/bench.py
openperf/benchmarks/data_science/bot_detection/bothawk.py
openperf/benchmarks/data_science/bot_detection/bothunter_bench.py
openperf/benchmarks/data_science/bot_detection/data/__init__.py
openperf/benchmarks/data_science/bot_detection/data/bothawk_BoDeGHa_data.csv
openperf/benchmarks/data_science/bot_detection/data/bothawk_bothunter_data.csv
openperf/benchmarks/data_science/bot_detection/data/bothawk_data.csv
openperf/benchmarks/index/__init__.py
openperf/benchmarks/index/activity_rank.py
openperf/benchmarks/index/influence_rank.py
openperf/benchmarks/index/models/__init__.py
openperf/benchmarks/index/models/activity_models.py
openperf/benchmarks/index/models/base_model.py
openperf/benchmarks/index/models/influence_models.py
openperf/benchmarks/index/rank/__init__.py
openperf/benchmarks/index/rank/activity.py
openperf/benchmarks/index/rank/influence.py
openperf/benchmarks/standard/__init__.py
openperf/benchmarks/standard/company/__init__.py
openperf/benchmarks/standard/company/activity.py
openperf/benchmarks/standard/company/influence.py
openperf/benchmarks/standard/developer/__init__.py
openperf/benchmarks/standard/developer/activity.py
openperf/benchmarks/standard/developer/influence.py
openperf/benchmarks/standard/project/__init__.py
openperf/benchmarks/standard/project/activity.py
openperf/benchmarks/standard/project/influence.py
openperf/data_management/__init__.py
openperf/data_management/data_cleaner.py
openperf/data_management/data_importer.py
openperf/data_management/data_loader.py
openperf/data_management/data_storage.py
openperf/data_management/data_transformer.py
openperf-0.1.dist-info/LICENSE.md
openperf-0.1.dist-info/METADATA
openperf-0.1.dist-info/WHEEL
openperf-0.1.dist-info/entry_points.txt
openperf-0.1.dist-info/top_level.txt
openperf-0.1.dist-info/RECORD
