Metadata-Version: 2.1
Name: openperf
Version: 0.1
Summary: OpenPerf is a benchmarking suite tailored for the sustainable management of open-source projects. It assesses key metrics and standards vital for the successful development of open-source ecosystems.
Home-page: https://github.com/X-lab2017/open-perf
Author: Fenglin Bi
Author-email: fenglin@stu.ecnu.edu.cn
Classifier: Development Status :: 4 - Beta
Classifier: Intended Audience :: Developers
Classifier: License :: OSI Approved :: MIT License
Classifier: Programming Language :: Python :: 3
Classifier: Programming Language :: Python :: 3.7
Classifier: Programming Language :: Python :: 3.8
Classifier: Programming Language :: Python :: 3.9
Classifier: License :: OSI Approved :: MIT License
License-File: LICENSE.md
Requires-Dist: certifi ==2024.2.2
Requires-Dist: charset-normalizer ==3.3.2
Requires-Dist: click ==8.1.7
Requires-Dist: idna ==3.7
Requires-Dist: imbalanced-learn ==0.12.2
Requires-Dist: joblib ==1.4.0
Requires-Dist: numpy ==1.26.4
Requires-Dist: pandas ==2.2.2
Requires-Dist: python-dateutil ==2.9.0.post0
Requires-Dist: pytz ==2024.1
Requires-Dist: requests ==2.31.0
Requires-Dist: scikit-learn ==1.1.1
Requires-Dist: scipy ==1.13.0
Requires-Dist: six ==1.16.0
Requires-Dist: threadpoolctl ==3.4.0
Requires-Dist: tzdata ==2024.1
Requires-Dist: urllib3 ==2.2.1
Requires-Dist: xgboost ==2.0.3
